andrewfoo/__init__.py
andrewfoo/list_ports.py
andrewfoo-0.0.6.dist-info/LICENSE.txt
andrewfoo-0.0.6.dist-info/METADATA
andrewfoo-0.0.6.dist-info/WHEEL
andrewfoo-0.0.6.dist-info/top_level.txt
andrewfoo-0.0.6.dist-info/RECORD
