Metadata-Version: 2.1
Name: andrewfoo
Version: 0.0.6
Summary: A small example package
Home-page: https://github.com/SEN-HUI/foo
Author: Suxin Li
Author-email: lisuxin4@gmail.com
License: MIT
Platform: UNKNOWN
Classifier: Programming Language :: Python :: 3
Classifier: License :: OSI Approved :: MIT License
Classifier: Operating System :: OS Independent
License-File: LICENSE.txt
Requires-Dist: pyserial (==3.5)
